.gitattributes
.gitignore
LICENSE
README.md
README_en.md
demo.py
sample_server.py
setup.py
whenconnect/__init__.py
whenconnect/api.py
whenconnect/config.py
whenconnect/logger.py
whenconnect/manager.py
whenconnect/scanner.py
whenconnect.egg-info/PKG-INFO
whenconnect.egg-info/SOURCES.txt
whenconnect.egg-info/dependency_links.txt
whenconnect.egg-info/requires.txt
whenconnect.egg-info/top_level.txt