Metadata-Version: 1.0
Name: whenconnect
Version: 0.5.4
Summary: when your android connected, do sth :) visit github page to view detail
Home-page: https://github.com/williamfzc/whenconnect
Author: williamfzc
Author-email: fengzc@vip.qq.com
License: UNKNOWN
Platform: UNKNOWN
